dash_feature_viewer/DashFeatureViewer.py
dash_feature_viewer/__init__.py
dash_feature_viewer/_imports_.py
dash_feature_viewer/dash_feature_viewer.min.js
dash_feature_viewer/dash_feature_viewer.min.js.map
dash_feature_viewer/metadata.json
dash_feature_viewer/package-info.json
dash_feature_viewer-0.0.1.dist-info/LICENSE
dash_feature_viewer-0.0.1.dist-info/METADATA
dash_feature_viewer-0.0.1.dist-info/WHEEL
dash_feature_viewer-0.0.1.dist-info/top_level.txt
dash_feature_viewer-0.0.1.dist-info/RECORD
