Metadata-Version: 2.1
Name: dash-feature-viewer
Version: 0.0.1
Summary: Calipho Feature Viewer for Dash
Home-page: UNKNOWN
Author: innoWADEtech <innowadetech@gmail.com>
License: MIT
Platform: UNKNOWN
Classifier: Framework :: Dash
License-File: LICENSE
Requires-Dist: dash (>=1.6.1)
